queens/__init__.py
queens/cli.py
queens/facade.py
queens/settings.py
queens/api/app.py
queens/config/etl_config.json
queens/config/schema.json
queens/config/templates.json
queens/config/urls.json
queens/config/templates/dukes_ch_1.xlsx
queens/config/templates/dukes_ch_2.xlsx
queens/config/templates/dukes_ch_3.xlsx
queens/config/templates/dukes_ch_4.xlsx
queens/config/templates/dukes_ch_5.xlsx
queens/config/templates/dukes_ch_6.xlsx
queens/config/templates/dukes_ch_7.xlsx
queens/core/read_write.py
queens/core/utils.py
queens/core/web_scraping.py
queens/etl/bootstrap.py
queens/etl/process.py
queens/etl/transformations.py
queens/etl/validation.py
queens-0.1.2.dist-info/METADATA
queens-0.1.2.dist-info/WHEEL
queens-0.1.2.dist-info/entry_points.txt
queens-0.1.2.dist-info/top_level.txt
queens-0.1.2.dist-info/RECORD
