Metadata-Version: 2.4
Name: queens
Version: 0.1.2
Summary: QUEENS (Queryable Energy National Statistics) — ETL + API + CLI for UK energy data.
Author: Alessandro Bigazzi
Project-URL: Homepage, https://github.com/queens
Project-URL: Repository, https://github.com/alebgz-91/queens
Project-URL: Issues, https://github.com/queens/issues
Project-URL: Documentation, https://github.com/queens/tree/main/docs
Classifier: Programming Language :: Python :: 3
Classifier: Programming Language :: Python :: 3 :: Only
Classifier: License :: OSI Approved :: MIT License
Classifier: Operating System :: OS Independent
Classifier: Topic :: Database
Classifier: Topic :: Scientific/Engineering :: Information Analysis
Classifier: Natural Language :: English
Requires-Python: >=3.9
Requires-Dist: pandas>=2.0
Requires-Dist: numpy>=1.23
Requires-Dist: fastapi<1,>=0.110
Requires-Dist: uvicorn>=0.22
Requires-Dist: typer>=0.9
Requires-Dist: requests>=2.31
Requires-Dist: openpyxl>=3.1
Requires-Dist: platformdirs>=4.0
Requires-Dist: beautifulsoup4>=4.12
Requires-Dist: tabulate>=0.9
Requires-Dist: pyarrow>=10
